pyxunlei/__init__.py
pyxunlei/pyxunlei.py
pyxunlei-0.1.8.dist-info/LICENSE
pyxunlei-0.1.8.dist-info/METADATA
pyxunlei-0.1.8.dist-info/WHEEL
pyxunlei-0.1.8.dist-info/RECORD
